tumeryk_guardrails/__init__.py
tumeryk_guardrails/guardrails_client.py
tumeryk_guardrails-0.3.1.dist-info/METADATA
tumeryk_guardrails-0.3.1.dist-info/WHEEL
tumeryk_guardrails-0.3.1.dist-info/top_level.txt
tumeryk_guardrails-0.3.1.dist-info/RECORD
