Metadata-Version: 2.4
Name: tumeryk_guardrails
Version: 0.3.1
Summary: API Client for Tumeryk Guardrails - OpenAI-compatible interface with AI safety guardrails
Home-page: https://tumeryk.com
Author: Tumeryk
Author-email: Tumeryk <support@tumeryk.com>
Project-URL: Homepage, https://tumeryk.com
Project-URL: Documentation, https://docs.tumeryk.com
Project-URL: Repository, https://github.com/tumeryk/tumeryk-guardrails-python
Keywords: tumeryk,guardrails,openai,llm,ai-safety,api-client
Classifier: Programming Language :: Python :: 3
Classifier: Programming Language :: Python :: 3.8
Classifier: Programming Language :: Python :: 3.9
Classifier: Programming Language :: Python :: 3.10
Classifier: Programming Language :: Python :: 3.11
Classifier: Programming Language :: Python :: 3.12
Classifier: Operating System :: OS Independent
Classifier: License :: OSI Approved :: MIT License
Classifier: Intended Audience :: Developers
Classifier: Topic :: Software Development :: Libraries :: Python Modules
Classifier: Topic :: Scientific/Engineering :: Artificial Intelligence
Requires-Python: >=3.8
Requires-Dist: requests>=2.25.0
Requires-Dist: aiohttp>=3.7.0
Provides-Extra: dev
Requires-Dist: pytest>=6.0; extra == "dev"
Requires-Dist: pytest-asyncio>=0.18.0; extra == "dev"
Requires-Dist: python-dotenv>=0.19.0; extra == "dev"
Dynamic: author
Dynamic: home-page
Dynamic: requires-python
